Metadata-Version: 2.4
Name: lcdp_deployment_manager
Version: 1.2.9
Summary: High level utilities to get/set AWS infrastructure items on prod
Home-page: https://github.com/LeComptoirDesPharmacies/lcdp-deployment-manager
Download-URL: https://github.com/LeComptoirDesPharmacies/lcdp-deployment-manager/archive/1.2.7.tar.gz
Author: Géry THRASIBULE
Author-email: g.thrasibule@lecomptoirdespharmacies.fr
License: MIT
Keywords: AWS,Python,Deployment
Classifier: Development Status :: 3 - Alpha
Classifier: Intended Audience :: Developers
Classifier: Topic :: Software Development :: Build Tools
Classifier: License :: OSI Approved :: MIT License
Classifier: Programming Language :: Python :: 3
License-File: LICENSE
Requires-Dist: boto3
Dynamic: author
Dynamic: author-email
Dynamic: classifier
Dynamic: description
Dynamic: description-content-type
Dynamic: download-url
Dynamic: home-page
Dynamic: keywords
Dynamic: license
Dynamic: license-file
Dynamic: requires-dist
Dynamic: summary
